{
	"textures": {
		"0": "animated_java:blueprint/dragonmounts/end",
		"particle": "minecraft:item/pufferfish"
	},
	"display": {
		"head": {
			"rotation": [0, 180, 0]
		}
	},
	"elements": [
		{
			"from": [-16, 5.42857, 5.42857],
			"to": [8, 10.57143, 10.57143],
			"rotation": {
				"angle": 0,
				"axis": "y",
				"origin": [17.42857, -29.71429, 38.85714]
			},
			"faces": {
				"north": {
					"uv": [2.125, 9.875, 0.375, 10.25],
					"texture": "#0"
				},
				"east": {
					"uv": [2.5, 9.875, 2.125, 10.25],
					"texture": "#0"
				},
				"south": {
					"uv": [4.25, 9.875, 2.5, 10.25],
					"texture": "#0"
				},
				"west": {
					"uv": [0.375, 9.875, 0, 10.25],
					"texture": "#0"
				},
				"up": {
					"uv": [0.375, 9.875, 2.125, 9.5],
					"texture": "#0"
				},
				"down": {
					"uv": [3.875, 9.875, 2.125, 9.5],
					"texture": "#0"
				}
			}
		},
		{
			"from": [-16, 7.12288, 8.94471],
			"to": [8, 7.12288, 26.94471],
			"rotation": {
				"angle": 0,
				"axis": "y",
				"origin": [17.42857, -30.59141, 37.23042]
			},
			"faces": {
				"north": {
					"uv": [8.75, 16, 10.5, 14.6875],
					"texture": "#0"
				},
				"east": {
					"uv": [8.75, 16, 10.5, 14.6875],
					"texture": "#0"
				},
				"south": {
					"uv": [8.75, 16, 10.5, 14.6875],
					"texture": "#0"
				},
				"west": {
					"uv": [8.75, 16, 10.5, 14.6875],
					"texture": "#0"
				},
				"up": {
					"uv": [8.75, 16, 10.5, 14.6875],
					"texture": "#0"
				},
				"down": {
					"uv": [8.75, 14.6875, 10.5, 16],
					"texture": "#0"
				}
			}
		}
	]
}